dytesproject/__init__.py
dytesproject-0.1.1.dist-info/WHEEL
dytesproject-0.1.1.dist-info/METADATA
dytesproject-0.1.1.dist-info/RECORD
