Metadata-Version: 2.1
Name: dytesproject
Version: 0.1.1
Summary: Dyens test project
Author: Kapustin Alexander
Author-email: akapustin@ambrahealth.com
Requires-Python: >=3.7,<4.0
Classifier: Programming Language :: Python :: 3
Classifier: Programming Language :: Python :: 3.7
Classifier: Programming Language :: Python :: 3.8
